qualia_core-2.5.0.dist-info/METADATA
qualia_core-2.5.0.dist-info/WHEEL
qualia_core-2.5.0.dist-info/entry_points.txt
qualia_core-2.5.0.dist-info/licenses/LICENSE
qualia_core/__init__.py
qualia_core/assets/__init__.py
qualia_core/assets/projects/stm32cubeai/NucleoL452REP/.cproject
qualia_core/assets/projects/stm32cubeai/NucleoL452REP/.gitignore
qualia_core/assets/projects/stm32cubeai/NucleoL452REP/.mxproject
qualia_core/assets/projects/stm32cubeai/NucleoL452REP/.project
qualia_core/assets/projects/stm32cubeai/NucleoL452REP/.settings/language.settings.xml
qualia_core/assets/projects/stm32cubeai/NucleoL452REP/.settings/stm32cubeide.project.prefs
qualia_core/assets/projects/stm32cubeai/NucleoL452REP/CMakeLists.txt
qualia_core/assets/projects/stm32cubeai/NucleoL452REP/Core/Inc/RTE_Components.h
qualia_core/assets/projects/stm32cubeai/NucleoL452REP/Core/Inc/main.h
qualia_core/assets/projects/stm32cubeai/NucleoL452REP/Core/Inc/stm32l4xx_hal_conf.h
qualia_core/assets/projects/stm32cubeai/NucleoL452REP/Core/Inc/stm32l4xx_it.h
qualia_core/assets/projects/stm32cubeai/NucleoL452REP/Core/Src/main.c
qualia_core/assets/projects/stm32cubeai/NucleoL452REP/Core/Src/stm32l4xx_hal_msp.c
qualia_core/assets/projects/stm32cubeai/NucleoL452REP/Core/Src/stm32l4xx_it.c
qualia_core/assets/projects/stm32cubeai/NucleoL452REP/Core/Src/syscalls.c
qualia_core/assets/projects/stm32cubeai/NucleoL452REP/Core/Src/sysmem.c
qualia_core/assets/projects/stm32cubeai/NucleoL452REP/Core/Src/system_stm32l4xx.c
qualia_core/assets/projects/stm32cubeai/NucleoL452REP/Core/Startup/startup_stm32l452retxp.s
qualia_core/assets/projects/stm32cubeai/NucleoL452REP/Drivers/CMSIS/Device/ST/STM32L4xx/Include/stm32l452xx.h
qualia_core/assets/projects/stm32cubeai/NucleoL452REP/Drivers/CMSIS/Device/ST/STM32L4xx/Include/stm32l4xx.h
qualia_core/assets/projects/stm32cubeai/NucleoL452REP/Drivers/CMSIS/Device/ST/STM32L4xx/Include/system_stm32l4xx.h
qualia_core/assets/projects/stm32cubeai/NucleoL452REP/Drivers/CMSIS/Device/ST/STM32L4xx/LICENSE.txt
qualia_core/assets/projects/stm32cubeai/NucleoL452REP/Drivers/CMSIS/Device/ST/STM32L4xx/License.md
qualia_core-2.5.0.dist-info/RECORD
