Metadata-Version: 2.1
Name: qualia-core
Version: 2.5.0
Summary: Qualia toolchain Core
Author-Email: Pierre-Emmanuel Novac <penovac@unice.fr>
License: AGPL-3.0-or-later
Classifier: Programming Language :: Python :: 3
Classifier: License :: OSI Approved :: GNU Affero General Public License v3
Classifier: Operating System :: OS Independent
Project-URL: homepage, https://github.com/LEAT-EDGE/qualia-core
Project-URL: documentation, https://leat-edge.github.io/qualia-core
Requires-Python: <3.14,>=3.9
Requires-Dist: numpy>=1.22.0
Requires-Dist: tomlkit>=0.11.7
Requires-Dist: colorful
Requires-Dist: gitpython
Requires-Dist: blosc2
Requires-Dist: pydantic
Requires-Dist: typing_extensions; python_version < "3.12"
Provides-Extra: codegen
Requires-Dist: qualia_codegen_core; extra == "codegen"
Provides-Extra: tensorflow
Requires-Dist: tensorflow<2.18.0rc0; extra == "tensorflow"
Requires-Dist: keras>=2.13.1; extra == "tensorflow"
Requires-Dist: pydot; extra == "tensorflow"
Provides-Extra: pytorch
Requires-Dist: torch; extra == "pytorch"
Requires-Dist: pytorch-lightning>=1.4.0; extra == "pytorch"
Requires-Dist: tabulate; extra == "pytorch"
Provides-Extra: gtsrb
Requires-Dist: imageio; extra == "gtsrb"
Requires-Dist: scikit-image; extra == "gtsrb"
Provides-Extra: gsc
Requires-Dist: torchaudio; extra == "gsc"
Provides-Extra: pytorch3drotation
Requires-Dist: pytorch3d; extra == "pytorch3drotation"
Provides-Extra: dataaugmentation-image
Requires-Dist: torchvision; extra == "dataaugmentation-image"
Provides-Extra: clearml
Requires-Dist: clearml; extra == "clearml"
Requires-Dist: tensorboard; extra == "clearml"
Provides-Extra: visualize
Requires-Dist: matplotlib; extra == "visualize"
Requires-Dist: pypdf; extra == "visualize"
Provides-Extra: deployment-sparkfunedge
Requires-Dist: pycryptodome; extra == "deployment-sparkfunedge"
Provides-Extra: evaluation-host-tflite
Requires-Dist: scikit-learn; extra == "evaluation-host-tflite"
Provides-Extra: evaluation-target-qualia
Requires-Dist: pyserial; extra == "evaluation-target-qualia"
Provides-Extra: tests
Requires-Dist: pytest; extra == "tests"
Requires-Dist: pytest-dependency; extra == "tests"
Requires-Dist: pytest-xdist; extra == "tests"
Requires-Dist: pytest-env; extra == "tests"
Requires-Dist: dill; extra == "tests"
Requires-Dist: filelock; extra == "tests"
Provides-Extra: lint
Requires-Dist: ruff; extra == "lint"
Provides-Extra: typecheck
Requires-Dist: mypy; extra == "typecheck"
Requires-Dist: pyright; extra == "typecheck"
Provides-Extra: docs
Requires-Dist: pdm; extra == "docs"
Requires-Dist: sphinx; extra == "docs"
Requires-Dist: sphinx-rtd-theme; extra == "docs"
Requires-Dist: myst-parser; extra == "docs"
